Workbook

Sheet Pivot Summary
A1: Disposition | B1: (Multiple Items) | D1: Count Open | E1: 317 | F1: Count Won | G1: 199 | H1: Count Total | I1: =E1+G1 -> 516
E2: =SUM(C5:C10)/E1 -> 0.2555205 | G2: =SUM(B5:B10)/G1 -> 0.10552764 | I2: =SUM(B5:C10)/I1 -> 0.19767442
A3: Count of Opp ID | B3: Column Labels
A4: Row Labels | B4: Closed Won SQL | C4: Open SQL
A5: 4A. Rate Uncompetitive | B5: 2 | C5: 12
A6: 4B. Ancillary Fees | B6: 10 | C6: 28
A7: 4C. Commercial Model | C7: 17
A8: 4D. Contract Mechanics | B8: 5 | C8: 11 | K8: 4A. Rate Uncompetitive | L8: 4B. Ancillary Fees | M8: 4C. Commercial Model | N8: 4D. Contract Mechanics | O8: 4E. Availability / Serviceability | P8: 4F. Promotion Ineligibility
A9: 4E. Availability / Serviceability | B9: 2 | C9: 11 | K9: 12 | L9: 28 | M9: 17 | N9: 11 | O9: 11 | P9: 2
A10: 4F. Promotion Ineligibility | B10: 2 | C10: 2 | K10: 2 | L10: 10 | N10: 5 | O10: 2 | P10: 2
A14: Disposition | B14: (Multiple Items) | E14: Disposition | F14: (Multiple Items) | I14: Disposition | J14: (Multiple Items)
A15: Code Name | B15: 4B. Ancillary Fees | E15: Code Name | F15: 4D. Contract Mechanics | I15: Code Name | J15: 4C. Commercial Model
A17: Count of Opp ID | B17: Column Labels | E17: Count of Opp ID | F17: Column Labels | I17: Count of Opp ID | J17: Column Labels
A18: Row Labels | B18: Closed Won SQL | C18: Open SQL | E18: Row Labels | F18: Closed Won SQL | G18: Open SQL | I18: Row Labels | J18: Open SQL
A19: install/objection | B19: 1 | C19: 7 | E19: process | F19: 4 | G19: 5 | I19: prebuy | J19: 8
A20: rental/economics | B20: 1 | C20: 4 | E20: exit-terms | G20: 3 | I20: ownership / purchase | J20: 4
A21: stack/economics | B21: 1 | C21: 4 | E21: payment-billing | G21: 2 | I21: commitment-length | J21: 4
A22: inspection/objection | B22: 4 | C22: 3 | E22: commitment-length | G22: 1 | I22: other | J22: 1
A23: stack/objection | C23: 2 | E23: other | F23: 1
A24: delivery/objection | C24: 2 | I24: Disposition | J24: (Multiple Items)
A25: stack | C25: 1 | I25: Code Name | J25: 4A. Rate Uncompetitive
A26: MUC/objection | C26: 1 | E26: Disposition | F26: (Multiple Items)
A27: install/economics | C27: 1 | E27: Code Name | F27: 4E. Availability / Serviceability | I27: Count of Opp ID | J27: Column Labels
A28: install | C28: 1 | I28: Row Labels | J28: Closed Won | K28: Open SQL
A29: rental/objection | B29: 2 | C29: 1 | E29: Count of Opp ID | F29: Column Labels | I29: current-supplier | K29: 6
A30: MUC/economics | C30: 1 | E30: Row Labels | F30: Closed Won SQL | G30: Open SQL | I30: competitor-rate | K30: 2
A31: inspection | B31: 1 | E31: equipment size | G31: 5 | I31: high-rate | K31: 2
E32: service timeline | F32: 2 | G32: 3 | I32: price-match | J32: 2 | K32: 1
E33: service capability | G33: 3 | I33: other | K33: 1

Sheet AI Output
A1: Version | B1: Batch | C1: Opp ID | D1: Salesforce Stage | E1: Rate | F1: Code | G1: Code Name | H1: Primary | I1: Qualifier | J1: Disposition | K1: Confidence | L1: Evidence | M1: Key | N1: Opp ID
A2: 5 | B2: 7 | C2: 006Rg00000aP8UEIA0 | D2: Open | E2: 1.93/gal | F2: — | G2: =_xlfn.XLOOKUP(M2,'Code Catagories'!A:A,'Code Catagories'!C:C) -> #N/A | H2: — | I2: — | J2: — | K2: — | L2: — | M2: =TRIM(F2) -> — | N2: =TRIM(C2) -> 006Rg00000aP8UEIA0
A3: 5 | B3: 7 | C3: 006Rg00000apbAUIAY | D3: Open | E3: — | F3: 4C | G3: =_xlfn.XLOOKUP(M3,'Code Catagories'!A:A,'Code Catagories'!C:C) -> 4C. Commercial Model | H3: Yes | I3: ownership | J3: hard_blocker | K3: High | L3: Customer wanted to purchase own tank; rep confirmed "we don't sell our tanks... not at this location"; customer went with alternate supplier. | M3: =TRIM(F3) -> 4C | N3: =TRIM(C3) -> 006Rg00000apbAUIAY
A4: 5 | B4: 7 | C4: 006Rg00000apbFJIAY | D4: Open | E4: 3.29/gal | F4: — | G4: =_xlfn.XLOOKUP(M4,'Code Catagories'!A:A,'Code Catagories'!C:C) -> #N/A | H4: — | I4: — | J4: — | K4: — | L4: — | M4: =TRIM(F4) -> — | N4: =TRIM(C4) -> 006Rg00000apbFJIAY
A5: 5 | B5: 7 | C5: 006Rg00000apIfjIAE | D5: Open | E5: 2.04V/2.15F/gal | F5: 4A | G5: =_xlfn.XLOOKUP(M5,'Code Catagories'!A:A,'Code Catagories'!C:C) -> 4A. Rate Uncompetitive | H5: Yes | I5: current-supplier | J5: hard_blocker | K5: High | L5: Customer's current supplier suddenly matched Superior's contract they previously refused; customer stayed with incumbent. | M5: =TRIM(F5) -> 4A | N5: =TRIM(C5) -> 006Rg00000apIfjIAE
A6: 5 | B6: 7 | C6: 006Rg00000aPmZaIAK | D6: Open | E6: 2.12/gal | F6: 4A | G6: =_xlfn.XLOOKUP(M6,'Code Catagories'!A:A,'Code Catagories'!C:C) -> 4A. Rate Uncompetitive | H6: — | I6: other | J6: mention_only | K6: Medium | L6: Customer noted parity with existing-customer lock rate: "same as me then. So I'm not getting any kind of special discount"; absorbed and signed at $2.12 fixed. | M6: =TRIM(F6) -> 4A | N6: =TRIM(C6) -> 006Rg00000aPmZaIAK
A7: 5 | B7: 7 | C7: 006Rg00000aPmZaIAK | D7: Open | E7: 2.12/gal | F7: 4C | G7: =_xlfn.XLOOKUP(M7,'Code Catagories'!A:A,'Code Catagories'!C:C) -> 4C. Commercial Model | H7: — | I7: rate-mechanism | J7: resolved | K7: Medium | L7: Customer feared year-2 rate could jump (e.g., $3.49/gal); rep explained price-cap protection; customer accepted "there's some consumer protection in there". | M7: =TRIM(F7) -> 4C | N7: =TRIM(C7) -> 006Rg00000aPmZaIAK
A8: 5 | B8: 7 | C8: 006Rg00000aPNBBIA4 | D8: Closed Won | E8: 2.181 ? 2.04/gal | F8: 4B | G8: =_xlfn.XLOOKUP(M8,'Code Catagories'!A:A,'Code Catagories'!C:C) -> 4B. Ancillary Fees | H8: — | I8: rental/economics | J8: mention_only | K8: Medium | L8: Customer uses ~250 gal/yr, below 400-gal waiver; will pay $99 rental; noted strategy to push usage over threshold; proceeded and signed. | M8: =TRIM(F8) -> 4B | N8: =TRIM(C8) -> 006Rg00000aPNBBIA4
A9: 5 | B9: 7 | C9: 006Rg00000aPNBBIA4 | D9: Closed Won | E9: 2.181 ? 2.04/gal | F9: 4C | G9: =_xlfn.XLOOKUP(M9,'Code Catagories'!A:A,'Code Catagories'!C:C) -> 4C. Commercial Model | H9: — | I9: ownership | J9: mention_only | K9: Medium | L9: Customer asked if Superior sells tanks and about self-install path; rep said office doesn't sell tanks; customer proceeded with lease. | M9: =TRIM(F9) -> 4C | N9: =TRIM(C9) -> 006Rg00000aPNBBIA4
A10: 5 | B10: 7 | C10: 006Rg00000aPqhpIAC | D10: Open | E10: — | F10: — | G10: =_xlfn.XLOOKUP(M10,'Code Catagories'!A:A,'Code Catagories'!C:C) -> #N/A | H10: — | I10: — | J10: insufficient_evidence | K10: Low | L10: All three segments are agent voicemails; no customer engagement on record; nothing evidentiary on any offer attribute. | M10: =TRIM(F10) -> — | N10: =TRIM(C10) -> 006Rg00000aPqhpIAC
A11: 5 | B11: 7 | C11: 006Rg00000apzW9IAI | D11: Open | E11: 2.04V/2.18F/gal | F11: 4B | G11: =_xlfn.XLOOKUP(M11,'Code Catagories'!A:A,'Code Catagories'!C:C) -> 4B. Ancillary Fees | H11: Yes | I11: install/objection | J11: friction | K11: Medium | L11: Trenching fee ($165/hr over 2 hrs) undetermined without site visit; customer expressed distrust of "hidden fees" and deferred decision to next week pending written fee schedule. | M11: =TRIM(F11) -> 4B | N11: =TRIM(C11) -> 006Rg00000apzW9IAI
A12: 5 | B12: 7 | C12: 006Rg00000aQ7AnIAK | D12: Closed Won | E12: 2.09/gal | F12: 4B | G12: =_xlfn.XLOOKUP(M12,'Code Catagories'!A:A,'Code Catagories'!C:C) -> 4B. Ancillary Fees | H12: — | I12: rental/objection | J12: mention_only | K12: Medium | L12: Customer uses ~300 gal/yr, below 400-gal waiver; will pay $99 annual rental on 250 tank; acknowledged and signed agreement. | M12: =TRIM(F12) -> 4B | N12: =TRIM(C12) -> 006Rg00000aQ7AnIAK
A13: 5 | B13: 7 | C13: 006Rg00000aQ7AnIAK | D13: Closed Won | E13: 2.09/gal | F13: 4D | G13: =_xlfn.XLOOKUP(M13,'Code Catagories'!A:A,'Code Catagories'!C:C) -> 4D. Contract Mechanics | H13: — | I13: commitment-length | J13: mention_only | K13: Medium | L13: Customer, a renter, asked about 3-year agreement liability; rep clarified exceptions for landlord-forced removals; customer proceeded and signed. | M13: =TRIM(F13) -> 4D | N13: =TRIM(C13) -> 006Rg00000aQ7AnIAK
... A115: 5 | B115: 13 | C115: 006Rg00000baVuPIAU | D115: Open | E115: 2.40/gal | F115: 4B | G115: =_xlfn.XLOOKUP(M115,'Code Catagories'!A:A,'Code Catagories'!C:C) -> 4B. Ancillary Fees | H115: Yes | I115: stack/economics | J115: friction | K115: Medium | L115: Employee-customer seasonal camper: new-install policy forces 120-gal min with $70 rental + $120 MUC = ~$190/yr fixed; customer said "probably beneficial just to keep the thirty pounders" and diverted to manager for exception rather than proceeding. | M115: =TRIM(F115) -> 4B | N115: =TRIM(C115) -> 006Rg00000baVuPIAU
A116: 4 | B116: 1 | C116: 006Rg00000a4cmjIAA | D116: Open | F116: 4F | G116: =_xlfn.XLOOKUP(M116,'Code Catagories'!A:A,'Code Catagories'!C:C) -> 4F. Promotion Ineligibility | H116: — | I116: prior-offer | J116: mention_only | K116: High | L116: Customer cited neighbor Phil's $1.99 Superior rate; rep explained tailored pricing; customer signed at $2.11 locked without concession. | M116: =TRIM(F116) -> 4F | N116: =TRIM(C116) -> 006Rg00000a4cmjIAA
A117: 4 | B117: 1 | C117: 006Rg00000a4cmjIAA | D117: Open | F117: 4C | G117: =_xlfn.XLOOKUP(M117,'Code Catagories'!A:A,'Code Catagories'!C:C) -> 4C. Commercial Model | H117: — | I117: prebuy | J117: mention_only | K117: High | L117: Customer normally pre-buys 500 gal in summer; rep said pre-buy only summer, offered lump-sum credit on account; customer accepted and signed. | M117: =TRIM(F117) -> 4C | N117: =TRIM(C117) -> 006Rg00000a4cmjIAA
A118: 4 | B118: 1 | C118: 006Rg00000a4cmjIAA | D118: Open | F118: 4D | G118: =_xlfn.XLOOKUP(M118,'Code Catagories'!A:A,'Code Catagories'!C:C) -> 4D. Contract Mechanics | H118: — | I118: exit-terms | J118: mention_only | K118: High | L118: Customer proactively asked about tank pickup fee citing AmeriGas history; accepted $250 pickup fee within 3-year term and signed. | M118: =TRIM(F118) -> 4D | N118: =TRIM(C118) -> 006Rg00000a4cmjIAA
A119: 4 | B119: 1 | C119: 006Rg00000a4glWIAQ | D119: Closed Won | F119: — | G119: =_xlfn.XLOOKUP(M119,'Code Catagories'!A:A,'Code Catagories'!C:C) -> #N/A | H119: — | I119: — | J119: — | K119: — | L119: — | M119: =TRIM(F119) -> — | N119: =TRIM(C119) -> 006Rg00000a4glWIAQ
A120: 4 | B120: 1 | C120: 006Rg00000a4NXeIAM | D120: Open | F120: 4C | G120: =_xlfn.XLOOKUP(M120,'Code Catagories'!A:A,'Code Catagories'!C:C) -> 4C. Commercial Model | H120: — | I120: ownership | J120: latent | K120: Medium | L120: Customer wanted to own tank; rep confirmed "we typically don't sell those size tanks"; opportunity ended undetermined pending daughter consult. | M120: =TRIM(F120) -> 4C | N120: =TRIM(C120) -> 006Rg00000a4NXeIAM
A121: 4 | B121: 1 | C121: 006Rg00000a4NXeIAM | D121: Open | F121: 4B | G121: =_xlfn.XLOOKUP(M121,'Code Catagories'!A:A,'Code Catagories'!C:C) -> 4B. Ancillary Fees | H121: — | I121: rental/economics | J121: mention_only | K121: Medium | L121: Rep disclosed $240/yr rental plus $120 MUC (~$360/yr) for ~50 gal/yr stove-only usage; customer noted budget but did not decline over fees. | M121: =TRIM(F121) -> 4B | N121: =TRIM(C121) -> 006Rg00000a4NXeIAM
A122: 4 | B122: 1 | C122: 006Rg00000a4NXeIAM | D122: Open | F122: 4E | G122: =_xlfn.XLOOKUP(M122,'Code Catagories'!A:A,'Code Catagories'!C:C) -> 4E. Availability / Serviceability | H122: — | I122: equipment | J122: mention_only | K122: Medium | L122: Rep could not fill customer's owned 100lb cylinder due to truck fill pressure; 120-gal rental tank offered as alternative path. | M122: =TRIM(F122) -> 4E | N122: =TRIM(C122) -> 006Rg00000a4NXeIAM
A123: 4 | B123: 1 | C123: 006Rg00000a4OLaIAM | D123: Open | F123: 4F | G123: =_xlfn.XLOOKUP(M123,'Code Catagories'!A:A,'Code Catagories'!C:C) -> 4F. Promotion Ineligibility | H123: — | I123: prior-offer | J123: mention_only | K123: Medium | L123: Customer expected free install because friend Donald "said to take it for free"; rep said promo not currently offered; customer conceded and continued. | M123: =TRIM(F123) -> 4F | N123: =TRIM(C123) -> 006Rg00000a4OLaIAM
A124: 4 | B124: 1 | C124: 006Rg00000a4OLaIAM | D124: Open | F124: 4B | G124: =_xlfn.XLOOKUP(M124,'Code Catagories'!A:A,'Code Catagories'!C:C) -> 4B. Ancillary Fees | H124: — | I124: delivery | J124: mention_only | K124: Medium | L124: Customer questioned delivery fee logic given proximity of trucks; rep explained fee covers delivery not proximity; customer accepted. | M124: =TRIM(F124) -> 4B | N124: =TRIM(C124) -> 006Rg00000a4OLaIAM
A125: 4 | B125: 1 | C125: 006Rg00000a4z8DIAQ | D125: Open | F125: — | G125: =_xlfn.XLOOKUP(M125,'Code Catagories'!A:A,'Code Catagories'!C:C) -> #N/A | H125: — | I125: — | J125: — | K125: — | L125: — | M125: =TRIM(F125) -> — | N125: =TRIM(C125) -> 006Rg00000a4z8DIAQ
A126: 4 | B126: 1 | C126: 006Rg00000a5bWtIAI | D126: Open | F126: 4C | G126: =_xlfn.XLOOKUP(M126,'Code Catagories'!A:A,'Code Catagories'!C:C) -> 4C. Commercial Model | H126: — | I126: ownership | J126: mention_only | K126: Medium | L126: Customer asked if rental applied toward ownership; rep confirmed rented tank only; customer said "okay" and continued engagement pending tank-ownership determination. | M126: =TRIM(F126) -> 4C | N126: =TRIM(C126) -> 006Rg00000a5bWtIAI
A127: 4 | B127: 1 | C127: 006Rg00000a5bWtIAI | D127: Open | F127: — | G127: =_xlfn.XLOOKUP(M127,'Code Catagories'!A:A,'Code Catagories'!C:C) -> #N/A | H127: — | I127: — | J127: — | K127: — | L127: — | M127: =TRIM(F127) -> — | N127: =TRIM(C127) -> 006Rg00000a5bWtIAI
... A238: 4 | B238: 6 | C238: 006Rg00000aP7CuIAK | D238: Open | F238: 4E | G238: =_xlfn.XLOOKUP(M238,'Code Catagories'!A:A,'Code Catagories'!C:C) -> 4E. Availability / Serviceability | H238: Yes | I238: equipment | J238: hard_blocker | K238: High | L238: Customer needed 48-gallon (200 lb) tank per campground rule; rep confirmed smallest available is [MASKED]-gallon; customer ended call on that basis. | M238: =TRIM(F238) -> 4E | N238: =TRIM(C238) -> 006Rg00000aP7CuIAK
A239: 5 | B239: 14 | C239: 006Rg00000bbIFCIA2 | D239: Open | E239: 2.10/gal | F239: 4D | G239: =_xlfn.XLOOKUP(M239,'Code Catagories'!A:A,'Code Catagories'!C:C) -> 4D. Contract Mechanics | H239: Yes | I239: process | J239: hard_blocker | K239: High | L239: Rep stated email is required to receive service; customer has no email and no smartphone ("flip phone"), cannot sign DocuSign; disengaged saying he would call back. | M239: =TRIM(F239) -> 4D | N239: =TRIM(C239) -> 006Rg00000bbIFCIA2
A240: 5 | B240: 14 | C240: 006Rg00000bbiROIAY | D240: Closed Won | E240: 2.55/gal | F240: — | G240: =_xlfn.XLOOKUP(M240,'Code Catagories'!A:A,'Code Catagories'!C:C) -> #N/A | H240: — | I240: — | J240: — | K240: — | L240: — | M240: =TRIM(F240) -> — | N240: =TRIM(C240) -> 006Rg00000bbiROIAY
A241: 5 | B241: 14 | C241: 006Rg00000bbjwvIAA | D241: Open | E241: 2.89F/2.74V/gal | F241: — | G241: =_xlfn.XLOOKUP(M241,'Code Catagories'!A:A,'Code Catagories'!C:C) -> #N/A | H241: — | I241: — | J241: — | K241: — | L241: — | M241: =TRIM(F241) -> — | N241: =TRIM(C241) -> 006Rg00000bbjwvIAA
A242: 5 | B242: 14 | C242: 006Rg00000bBl1WIAS | D242: Open | E242: 4.69/gal | F242: — | G242: =_xlfn.XLOOKUP(M242,'Code Catagories'!A:A,'Code Catagories'!C:C) -> #N/A | H242: — | I242: — | J242: — | K242: — | L242: — | M242: =TRIM(F242) -> — | N242: =TRIM(C242) -> 006Rg00000bBl1WIAS
A243: 5 | B243: 14 | C243: 006Rg00000bBnPuIAK | D243: Open | E243: 1.59/1.73/gal | F243: — | G243: =_xlfn.XLOOKUP(M243,'Code Catagories'!A:A,'Code Catagories'!C:C) -> #N/A | H243: — | I243: — | J243: — | K243: — | L243: — | M243: =TRIM(F243) -> — | N243: =TRIM(C243) -> 006Rg00000bBnPuIAK
A244: 5 | B244: 14 | C244: 006Rg00000bBnuYIAS | D244: Closed Won | E244: 2.27/gal | F244: — | G244: =_xlfn.XLOOKUP(M244,'Code Catagories'!A:A,'Code Catagories'!C:C) -> #N/A | H244: — | I244: — | J244: — | K244: — | L244: — | M244: =TRIM(F244) -> — | N244: =TRIM(C244) -> 006Rg00000bBnuYIAS
A245: 5 | B245: 14 | C245: 006Rg00000bC1kdIAC | D245: Open | E245: — | F245: — | G245: =_xlfn.XLOOKUP(M245,'Code Catagories'!A:A,'Code Catagories'!C:C) -> #N/A | H245: — | I245: — | J245: — | K245: — | L245: — | M245: =TRIM(F245) -> — | N245: =TRIM(C245) -> 006Rg00000bC1kdIAC
A246: 5 | B246: 14 | C246: 006Rg00000bC3b8IAC | D246: Closed Won | E246: — | F246: — | G246: =_xlfn.XLOOKUP(M246,'Code Catagories'!A:A,'Code Catagories'!C:C) -> #N/A | H246: — | I246: — | J246: — | K246: — | L246: — | M246: =TRIM(F246) -> — | N246: =TRIM(C246) -> 006Rg00000bC3b8IAC
A247: 5 | B247: 14 | C247: 006Rg00000bC5oGIAS | D247: Closed Won | E247: 2.02/gal | F247: — | G247: =_xlfn.XLOOKUP(M247,'Code Catagories'!A:A,'Code Catagories'!C:C) -> #N/A | H247: — | I247: — | J247: — | K247: — | L247: — | M247: =TRIM(F247) -> — | N247: =TRIM(C247) -> 006Rg00000bC5oGIAS
A248: 5 | B248: 14 | C248: 006Rg00000bCTH3IAO | D248: Closed Won | E248: 1.43V/1.58F/gal | F248: — | G248: =_xlfn.XLOOKUP(M248,'Code Catagories'!A:A,'Code Catagories'!C:C) -> #N/A | H248: — | I248: — | J248: — | K248: — | L248: — | M248: =TRIM(F248) -> — | N248: =TRIM(C248) -> 006Rg00000bCTH3IAO
A249: 5 | B249: 14 | C249: 006Rg00000bD9hhIAC | D249: Closed Won | E249: 2.24 ? 2.27/gal | F249: — | G249: =_xlfn.XLOOKUP(M249,'Code Catagories'!A:A,'Code Catagories'!C:C) -> #N/A | H249: — | I249: — | J249: — | K249: — | L249: — | M249: =TRIM(F249) -> — | N249: =TRIM(C249) -> 006Rg00000bD9hhIAC
A250: 5 | B250: 14 | C250: 006Rg00000bde0HIAQ | D250: Open | E250: 1.86/gal | F250: — | G250: =_xlfn.XLOOKUP(M250,'Code Catagories'!A:A,'Code Catagories'!C:C) -> #N/A | H250: — | I250: — | J250: — | K250: — | L250: — | M250: =TRIM(F250) -> — | N250: =TRIM(C250) -> 006Rg00000bde0HIAQ
... A580: 5 | B580: 37 | C580: 006Rg00000czMNVIA2 | D580: Closed Won | E580: 1.92/gal | F580: — | G580: =_xlfn.XLOOKUP(M580,'Code Catagories'!A:A,'Code Catagories'!C:C) -> #N/A | H580: — | I580: — | J580: — | K580: — | L580: — | M580: =TRIM(F580) -> — | N580: =TRIM(C580) -> 006Rg00000czMNVIA2

Sheet Backup->
F5: 006Rg00000aP8UEIA0
F6: 006Rg00000apbAUIAY | J6: 006Rg00000aPNBBIA4
F7: 006Rg00000apbFJIAY | J7: 006Rg00000aQ7AnIAK
F8: 006Rg00000apIfjIAE | J8: 006Rg00000aQKsnIAG
F9: 006Rg00000aPmZaIAK | J9: 006Rg00000aRcGIIA0
F10: 006Rg00000aPqhpIAC | J10: 006Rg00000aRqp1IAC
F11: 006Rg00000apzW9IAI | J11: 006Rg00000aRv8jIAC
F12: 006Rg00000aqHJfIAM | J12: 006Rg00000aS8VpIAK
F13: 006Rg00000aqUuvIAE | J13: 006Rg00000aSenQIAS
F14: 006Rg00000aSCkhIAG | J14: 006Rg00000aSRwbIAG
F15: 006Rg00000aSE9lIAG | J15: 006Rg00000aTAdbIAG
F16: 006Rg00000aSgxHIAS | J16: 006Rg00000aTQtdIAG
F17: 006Rg00000aSHsQIAW | J17: 006Rg00000auz5lIAA
... F48: 006Rg00000b3oRCIAY | J48: 006Rg00000b75s5IAA
F49: 006Rg00000b3qWGIAY
F50: 006Rg00000b3XIJIA2
F51: 006Rg00000b4kerIAA
F52: 006Rg00000b4u37IAA
F53: 006Rg00000b6HorIAE
F54: 006Rg00000b6k4VIAQ
F55: 006Rg00000b6L4TIAU
F56: 006Rg00000b6o3FIAQ
F57: 006Rg00000b6QdgIAE
F58: 006Rg00000b7h4XIAQ
F59: 006Rg00000b7REHIA2
F60: 006Rg00000b7snyIAA
... F67: 006Rg00000baVuPIAU

Sheet Code Catagories
A1: Code | B1: Catagory | C1: Description | D1: Definition
A2: 4A | B2: 4. Product/Offer Issues | C2: 4A. Rate Uncompetitive | D2: Rate objectively >$2.30/gal residential OR explicit rejection. Does NOT include total economics where fees are killer (that's 4C).
A3: 4B | B3: 4. Product/Offer Issues | C3: 4B. Ancillary Fees | D3: Fees breaking economics on offers Superior DOES provide. Primary for low-volume MUC/rental issues. v5.5: Includes Ontario $199 TSSA 10-year inspection when customer objects.
A4: 4C | B4: 4. Product/Offer Issues | C4: 4C. Commercial Model | D4: Fixed vs variable, no pre-buy, Year-2 uncertainty, rate caps, min consumption
A5: 4D | B5: 4. Product/Offer Issues | C5: 4D. Contract Mechanics | D5: Cancellation/exit ($500/$250 tiered Ontario + $250 equipment removal), payment/billing terms
A6: 4E | B6: 4. Product/Offer Issues | C6: 4E. Availability / Serviceability | D6: ONLY for offers Superior structurally does NOT provide (no 100lb cylinders, no RV, no food truck TSSA, service area limits). NOT for oil (Superior sells oil). NOT for low-volume customers where fees just make it uneconomical (that's 4C).
A7: 4F | B7: 4. Product/Offer Issues | C7: 4F. Promotion Ineligibility | D7: Volume-gated, auto-delivery gate, credit gate, discount too small. v5.5 NEW TRIGGER: Referral discount is one-way - referrer gets credit but new customer does not. 'Do we get any discounts for being referred?' indicates confusion.
